lolzapi
