Metadata-Version: 2.1
Name: lolzapi
Version: 0.4.0
Summary: Простое апи для lolz.guru
Home-page: UNKNOWN
Author-email: cotanton111@gmail.com
License: UNKNOWN
Platform: UNKNOWN
